__init__.py
computing_toolbox/__init__.py
computing_toolbox/algorithms/__init__.py
computing_toolbox/algorithms/shrink_list_to_interval_string.py
computing_toolbox/algorithms/split_range.py
computing_toolbox/cli/__init__.py
computing_toolbox/cli/es_long_search_cli.py
computing_toolbox/gcp/__init__.py
computing_toolbox/gcp/gs.py
computing_toolbox/gcp/gs_async.py
computing_toolbox/gcp/pubsub.py
computing_toolbox/gcp/secret_manager.py
computing_toolbox/utils/__init__.py
computing_toolbox/utils/cprint.py
computing_toolbox/utils/dedup.py
computing_toolbox/utils/deep_get.py
computing_toolbox/utils/deep_key.py
computing_toolbox/utils/es_long_search.py
computing_toolbox/utils/es_long_search_generator.py
computing_toolbox/utils/http_async_request.py
computing_toolbox/utils/http_fake_headers.py
computing_toolbox/utils/http_request.py
computing_toolbox/utils/jsonl.py
computing_toolbox/utils/lsr.py
computing_toolbox/utils/tictoc.py
computing_toolbox-1.6.11.dist-info/LICENSE
computing_toolbox-1.6.11.dist-info/METADATA
computing_toolbox-1.6.11.dist-info/WHEEL
computing_toolbox-1.6.11.dist-info/entry_points.txt
computing_toolbox-1.6.11.dist-info/top_level.txt
computing_toolbox-1.6.11.dist-info/RECORD
