Metadata-Version: 2.1
Name: computing-toolbox
Version: 1.6.11
Summary: Computing Toolbox for daily computations
Author-email: Pedro Mayorga <ppmayorga80@gmail.com>
Classifier: Programming Language :: Python :: 3
Classifier: License :: OSI Approved :: MIT License
Classifier: Operating System :: OS Independent
Requires-Python: >=3.7
License-File: LICENSE
Requires-Dist: aiohttp ~=3.8.4
Requires-Dist: aioresponses ~=0.7.4
Requires-Dist: art ==6.1
Requires-Dist: colorama ==0.4.6
Requires-Dist: docopt ==0.6.2
Requires-Dist: elasticsearch ~=7.13.4
Requires-Dist: fake-headers ~=1.0.2
Requires-Dist: gcloud-aio-storage ~=8.2.0
Requires-Dist: google-cloud-monitoring ~=2.15.1
Requires-Dist: google-cloud-pubsub ~=2.18.0
Requires-Dist: google-cloud-secret-manager ~=2.16.2
Requires-Dist: google-cloud-storage ~=2.10.0
Requires-Dist: jsons ~=1.6.3
Requires-Dist: pandas ~=2.0.3
Requires-Dist: python-dateutil ~=2.8.2
Requires-Dist: python-dotenv ~=1.0.0
Requires-Dist: smart-open ~=6.3.0
Requires-Dist: tqdm ~=4.66.1
